diepvries/__init__.py
diepvries/data_vault_load.py
diepvries/driving_key_field.py
diepvries/effectivity_satellite.py
diepvries/field.py
diepvries/hub.py
diepvries/link.py
diepvries/py.typed
diepvries/role_playing_hub.py
diepvries/satellite.py
diepvries/table.py
diepvries/deserializers/__init__.py
diepvries/deserializers/snowflake_deserializer.py
diepvries/deserializers/snowflake_model_metadata.sql
diepvries/template_sql/__init__.py
diepvries/template_sql/effectivity_satellite_dml.sql
diepvries/template_sql/hub_link_dml.sql
diepvries/template_sql/satellite_dml.sql
diepvries/template_sql/sql_formulas.py
diepvries/template_sql/staging_table_ddl.sql
diepvries-2.0.0.dist-info/licenses/LICENSE
diepvries-2.0.0.dist-info/METADATA
diepvries-2.0.0.dist-info/WHEEL
diepvries-2.0.0.dist-info/top_level.txt
diepvries-2.0.0.dist-info/RECORD
