Metadata-Version: 2.4
Name: diepvries
Version: 2.0.0
Summary: diepvries - Picnic Data Vault framework
Author: Picnic Technologies
License: MIT License
Project-URL: Documentation, https://diepvries.picnic.tech/
Project-URL: Source Code, https://github.com/PicnicSupermarket/diepvries
Project-URL: Issue Tracker, https://github.com/PicnicSupermarket/diepvries/issues
Keywords: data vault
Classifier: License :: OSI Approved :: MIT License
Classifier: Programming Language :: Python :: 3
Classifier: Intended Audience :: Developers
Classifier: Operating System :: OS Independent
Requires-Python: >=3.10
License-File: LICENSE
Requires-Dist: snowflake-connector-python[secure-local-storage]~=4.1
Provides-Extra: test
Requires-Dist: pytest~=6.2; extra == "test"
Provides-Extra: dev
Requires-Dist: pytest~=6.2; extra == "dev"
Requires-Dist: tox; extra == "dev"
Requires-Dist: pre-commit; extra == "dev"
Dynamic: license-file
